[
  {
    "file": "_analyze/install.sql",
    "tables": [],
    "functions": [
      {
        "name": "pgfr_analyze.modification_rate",
        "line": 22,
        "returns": "numeric"
      },
      {
        "name": "pgfr_analyze.hot_update_ratio",
        "line": 76,
        "returns": "numeric"
      },
      {
        "name": "pgfr_analyze.anomaly_report",
        "line": 105,
        "returns": "record"
      },
      {
        "name": "pgfr_analyze.summary_report",
        "line": 477,
        "returns": "record"
      },
      {
        "name": "pgfr_analyze.detect_query_storms",
        "line": 595,
        "returns": "record"
      },
      {
        "name": "pgfr_analyze._diagnose_regression_causes",
        "line": 720,
        "returns": "text"
      },
      {
        "name": "pgfr_analyze.detect_regressions",
        "line": 793,
        "returns": "record"
      },
      {
        "name": "pgfr_analyze.performance_report",
        "line": 955,
        "returns": "record"
      },
      {
        "name": "pgfr_analyze.check_alerts",
        "line": 1107,
        "returns": "record"
      },
      {
        "name": "pgfr_analyze.report",
        "line": 1197,
        "returns": "text"
      },
      {
        "name": "pgfr_analyze.report",
        "line": 1197,
        "returns": "text"
      },
      {
        "name": "pgfr_analyze.preflight_check",
        "line": 1607,
        "returns": "record"
      },
      {
        "name": "pgfr_analyze.preflight_check_with_summary",
        "line": 1728,
        "returns": "record"
      },
      {
        "name": "pgfr_analyze.quarterly_review",
        "line": 1772,
        "returns": "record"
      },
      {
        "name": "pgfr_analyze.quarterly_review_with_summary",
        "line": 1975,
        "returns": "record"
      },
      {
        "name": "pgfr_analyze.capacity_summary",
        "line": 2010,
        "returns": "record"
      },
      {
        "name": "pgfr_analyze.capacity_report",
        "line": 2381,
        "returns": "text"
      },
      {
        "name": "pgfr_analyze.table_compare",
        "line": 2614,
        "returns": "record"
      },
      {
        "name": "pgfr_analyze.table_hotspots",
        "line": 2711,
        "returns": "record"
      },
      {
        "name": "pgfr_analyze.unused_indexes",
        "line": 2808,
        "returns": "record"
      },
      {
        "name": "pgfr_analyze.index_efficiency",
        "line": 2867,
        "returns": "record"
      },
      {
        "name": "pgfr_analyze.config_changes",
        "line": 2935,
        "returns": "record"
      },
      {
        "name": "pgfr_analyze.config_at",
        "line": 2982,
        "returns": "record"
      },
      {
        "name": "pgfr_analyze.config_health_check",
        "line": 3008,
        "returns": "record"
      },
      {
        "name": "pgfr_analyze.db_role_config_at",
        "line": 3088,
        "returns": "record"
      },
      {
        "name": "pgfr_analyze.db_role_config_changes",
        "line": 3127,
        "returns": "record"
      },
      {
        "name": "pgfr_analyze.db_role_config_summary",
        "line": 3182,
        "returns": "record"
      },
      {
        "name": "pgfr_analyze.what_happened_at",
        "line": 3234,
        "returns": "record"
      },
      {
        "name": "pgfr_analyze.incident_timeline",
        "line": 3674,
        "returns": "record"
      },
      {
        "name": "pgfr_analyze.blast_radius",
        "line": 3878,
        "returns": "record"
      },
      {
        "name": "pgfr_analyze.blast_radius_report",
        "line": 4382,
        "returns": "text"
      }
    ],
    "views": [
      {
        "name": "pgfr_analyze.capacity_dashboard",
        "line": 2482
      }
    ],
    "types": []
  },
  {
    "file": "_control/install.sql",
    "tables": [
      {
        "name": "pgfr_control.vacuum_control_state",
        "line": 27,
        "columns": [
          {
            "name": "relid",
            "type": "oid",
            "line": 28
          },
          {
            "name": "operating_mode",
            "type": "text",
            "line": 29
          },
          {
            "name": "mode_entered_at",
            "type": "timestamptz",
            "line": 30
          },
          {
            "name": "last_recommendation_at",
            "type": "timestamptz",
            "line": 31
          },
          {
            "name": "last_recommended_scale_factor",
            "type": "numeric",
            "line": 32
          },
          {
            "name": "consecutive_budget_exceeded",
            "type": "int4",
            "line": 33
          },
          {
            "name": "updated_at",
            "type": "timestamptz",
            "line": 34
          }
        ]
      }
    ],
    "functions": [
      {
        "name": "pgfr_control.dead_tuple_growth_rate",
        "line": 44,
        "returns": "numeric"
      },
      {
        "name": "pgfr_control.time_to_budget_exhaustion",
        "line": 95,
        "returns": "interval"
      },
      {
        "name": "pgfr_control._get_table_autovacuum_settings",
        "line": 147,
        "returns": "record"
      },
      {
        "name": "pgfr_control.dead_tuple_trend",
        "line": 202,
        "returns": "numeric"
      },
      {
        "name": "pgfr_control.vacuum_control_mode",
        "line": 235,
        "returns": "record"
      },
      {
        "name": "pgfr_control.compute_recommended_scale_factor",
        "line": 354,
        "returns": "record"
      },
      {
        "name": "pgfr_control.vacuum_diagnostic",
        "line": 458,
        "returns": "record"
      },
      {
        "name": "pgfr_control.vacuum_control_report",
        "line": 588,
        "returns": "record"
      },
      {
        "name": "pgfr_control.dead_tuple_growth_rate",
        "line": 44,
        "returns": "numeric"
      },
      {
        "name": "pgfr_control.table_size_growth_rate",
        "line": 780,
        "returns": "numeric"
      },
      {
        "name": "pgfr_control.estimate_table_bloat",
        "line": 833,
        "returns": "record"
      },
      {
        "name": "pgfr_control.bloat_report",
        "line": 934,
        "returns": "record"
      },
      {
        "name": "pgfr_control.time_to_budget_exhaustion",
        "line": 95,
        "returns": "interval"
      },
      {
        "name": "pgfr_control.oid_consumption_rate",
        "line": 1065,
        "returns": "numeric"
      },
      {
        "name": "pgfr_control.time_to_oid_exhaustion",
        "line": 1111,
        "returns": "interval"
      }
    ],
    "views": [],
    "types": []
  },
  {
    "file": "_record/install.sql",
    "tables": [
      {
        "name": "pgfr.snapshots",
        "line": 36,
        "columns": [
          {
            "name": "id",
            "type": "serial",
            "line": 37
          },
          {
            "name": "captured_at",
            "type": "timestamptz",
            "line": 38
          },
          {
            "name": "pg_version",
            "type": "int4",
            "line": 39
          },
          {
            "name": "wal_records",
            "type": "int8",
            "line": 40
          },
          {
            "name": "wal_fpi",
            "type": "int8",
            "line": 41
          },
          {
            "name": "wal_bytes",
            "type": "int8",
            "line": 42
          },
          {
            "name": "wal_write_time",
            "type": "float8",
            "line": 43
          },
          {
            "name": "wal_sync_time",
            "type": "float8",
            "line": 44
          },
          {
            "name": "checkpoint_lsn",
            "type": "pg_lsn",
            "line": 45
          },
          {
            "name": "checkpoint_time",
            "type": "timestamptz",
            "line": 46
          },
          {
            "name": "ckpt_timed",
            "type": "int8",
            "line": 47
          },
          {
            "name": "ckpt_requested",
            "type": "int8",
            "line": 48
          },
          {
            "name": "ckpt_write_time",
            "type": "float8",
            "line": 49
          },
          {
            "name": "ckpt_sync_time",
            "type": "float8",
            "line": 50
          },
          {
            "name": "ckpt_buffers",
            "type": "int8",
            "line": 51
          },
          {
            "name": "bgw_buffers_clean",
            "type": "int8",
            "line": 52
          },
          {
            "name": "bgw_maxwritten_clean",
            "type": "int8",
            "line": 53
          },
          {
            "name": "bgw_buffers_alloc",
            "type": "int8",
            "line": 54
          },
          {
            "name": "bgw_buffers_backend",
            "type": "int8",
            "line": 55
          },
          {
            "name": "bgw_buffers_backend_fsync",
            "type": "int8",
            "line": 56
          },
          {
            "name": "autovacuum_workers",
            "type": "int4",
            "line": 57
          },
          {
            "name": "slots_count",
            "type": "int4",
            "line": 58
          },
          {
            "name": "slots_max_retained_wal",
            "type": "int8",
            "line": 59
          },
          {
            "name": "io_checkpointer_reads",
            "type": "int8",
            "line": 60
          },
          {
            "name": "io_checkpointer_read_time",
            "type": "float8",
            "line": 61
          },
          {
            "name": "io_checkpointer_writes",
            "type": "int8",
            "line": 62
          },
          {
            "name": "io_checkpointer_write_time",
            "type": "float8",
            "line": 63
          },
          {
            "name": "io_checkpointer_fsyncs",
            "type": "int8",
            "line": 64
          },
          {
            "name": "io_checkpointer_fsync_time",
            "type": "float8",
            "line": 65
          },
          {
            "name": "io_autovacuum_reads",
            "type": "int8",
            "line": 66
          },
          {
            "name": "io_autovacuum_read_time",
            "type": "float8",
            "line": 67
          },
          {
            "name": "io_autovacuum_writes",
            "type": "int8",
            "line": 68
          },
          {
            "name": "io_autovacuum_write_time",
            "type": "float8",
            "line": 69
          },
          {
            "name": "io_client_reads",
            "type": "int8",
            "line": 70
          },
          {
            "name": "io_client_read_time",
            "type": "float8",
            "line": 71
          },
          {
            "name": "io_client_writes",
            "type": "int8",
            "line": 72
          },
          {
            "name": "io_client_write_time",
            "type": "float8",
            "line": 73
          },
          {
            "name": "io_bgwriter_reads",
            "type": "int8",
            "line": 74
          },
          {
            "name": "io_bgwriter_read_time",
            "type": "float8",
            "line": 75
          },
          {
            "name": "io_bgwriter_writes",
            "type": "int8",
            "line": 76
          },
          {
            "name": "io_bgwriter_write_time",
            "type": "float8",
            "line": 77
          },
          {
            "name": "temp_files",
            "type": "int8",
            "line": 78
          },
          {
            "name": "temp_bytes",
            "type": "int8",
            "line": 79
          },
          {
            "name": "xact_commit",
            "type": "int8",
            "line": 80
          },
          {
            "name": "xact_rollback",
            "type": "int8",
            "line": 81
          },
          {
            "name": "blks_read",
            "type": "int8",
            "line": 82
          },
          {
            "name": "blks_hit",
            "type": "int8",
            "line": 83
          },
          {
            "name": "connections_active",
            "type": "int4",
            "line": 84
          },
          {
            "name": "connections_total",
            "type": "int4",
            "line": 85
          },
          {
            "name": "connections_max",
            "type": "int4",
            "line": 86
          },
          {
            "name": "db_size_bytes",
            "type": "int8",
            "line": 87
          },
          {
            "name": "datfrozenxid_age",
            "type": "int4",
            "line": 88
          },
          {
            "name": "archived_count",
            "type": "int8",
            "line": 89
          },
          {
            "name": "last_archived_wal",
            "type": "text",
            "line": 90
          },
          {
            "name": "last_archived_time",
            "type": "timestamptz",
            "line": 91
          },
          {
            "name": "failed_count",
            "type": "int8",
            "line": 92
          },
          {
            "name": "last_failed_wal",
            "type": "text",
            "line": 93
          },
          {
            "name": "last_failed_time",
            "type": "timestamptz",
            "line": 94
          },
          {
            "name": "archiver_stats_reset",
            "type": "timestamptz",
            "line": 95
          },
          {
            "name": "confl_tablespace",
            "type": "int8",
            "line": 96
          },
          {
            "name": "confl_lock",
            "type": "int8",
            "line": 97
          },
          {
            "name": "confl_snapshot",
            "type": "int8",
            "line": 98
          },
          {
            "name": "confl_bufferpin",
            "type": "int8",
            "line": 99
          },
          {
            "name": "confl_deadlock",
            "type": "int8",
            "line": 100
          },
          {
            "name": "confl_active_logicalslot",
            "type": "int8",
            "line": 101
          },
          {
            "name": "max_catalog_oid",
            "type": "int8",
            "line": 102
          },
          {
            "name": "large_object_count",
            "type": "int8",
            "line": 103
          }
        ]
      },
      {
        "name": "pgfr.replication_snapshots",
        "line": 110,
        "columns": [
          {
            "name": "snapshot_id",
            "type": "int4",
            "line": 111
          },
          {
            "name": "pid",
            "type": "int4",
            "line": 112
          },
          {
            "name": "client_addr",
            "type": "inet",
            "line": 113
          },
          {
            "name": "application_name",
            "type": "text",
            "line": 114
          },
          {
            "name": "state",
            "type": "text",
            "line": 115
          },
          {
            "name": "sync_state",
            "type": "text",
            "line": 116
          },
          {
            "name": "sent_lsn",
            "type": "pg_lsn",
            "line": 117
          },
          {
            "name": "write_lsn",
            "type": "pg_lsn",
            "line": 118
          },
          {
            "name": "flush_lsn",
            "type": "pg_lsn",
            "line": 119
          },
          {
            "name": "replay_lsn",
            "type": "pg_lsn",
            "line": 120
          },
          {
            "name": "write_lag",
            "type": "interval",
            "line": 121
          },
          {
            "name": "flush_lag",
            "type": "interval",
            "line": 122
          },
          {
            "name": "replay_lag",
            "type": "interval",
            "line": 123
          }
        ]
      },
      {
        "name": "pgfr.vacuum_progress_snapshots",
        "line": 130,
        "columns": [
          {
            "name": "snapshot_id",
            "type": "int4",
            "line": 131
          },
          {
            "name": "pid",
            "type": "int4",
            "line": 132
          },
          {
            "name": "datid",
            "type": "oid",
            "line": 133
          },
          {
            "name": "datname",
            "type": "text",
            "line": 134
          },
          {
            "name": "relid",
            "type": "oid",
            "line": 135
          },
          {
            "name": "relname",
            "type": "text",
            "line": 136
          },
          {
            "name": "phase",
            "type": "text",
            "line": 137
          },
          {
            "name": "heap_blks_total",
            "type": "int8",
            "line": 138
          },
          {
            "name": "heap_blks_scanned",
            "type": "int8",
            "line": 139
          },
          {
            "name": "heap_blks_vacuumed",
            "type": "int8",
            "line": 140
          },
          {
            "name": "index_vacuum_count",
            "type": "int8",
            "line": 141
          },
          {
            "name": "max_dead_tuples",
            "type": "int8",
            "line": 142
          },
          {
            "name": "num_dead_tuples",
            "type": "int8",
            "line": 143
          }
        ]
      },
      {
        "name": "pgfr.statement_snapshots",
        "line": 151,
        "columns": [
          {
            "name": "snapshot_id",
            "type": "int4",
            "line": 152
          },
          {
            "name": "queryid",
            "type": "int8",
            "line": 153
          },
          {
            "name": "userid",
            "type": "oid",
            "line": 154
          },
          {
            "name": "dbid",
            "type": "oid",
            "line": 155
          },
          {
            "name": "query_preview",
            "type": "text",
            "line": 156
          },
          {
            "name": "calls",
            "type": "int8",
            "line": 157
          },
          {
            "name": "total_exec_time",
            "type": "float8",
            "line": 158
          },
          {
            "name": "min_exec_time",
            "type": "float8",
            "line": 159
          },
          {
            "name": "max_exec_time",
            "type": "float8",
            "line": 160
          },
          {
            "name": "mean_exec_time",
            "type": "float8",
            "line": 161
          },
          {
            "name": "rows",
            "type": "int8",
            "line": 162
          },
          {
            "name": "shared_blks_hit",
            "type": "int8",
            "line": 163
          },
          {
            "name": "shared_blks_read",
            "type": "int8",
            "line": 164
          },
          {
            "name": "shared_blks_dirtied",
            "type": "int8",
            "line": 165
          },
          {
            "name": "shared_blks_written",
            "type": "int8",
            "line": 166
          },
          {
            "name": "temp_blks_read",
            "type": "int8",
            "line": 167
          },
          {
            "name": "temp_blks_written",
            "type": "int8",
            "line": 168
          },
          {
            "name": "blk_read_time",
            "type": "float8",
            "line": 169
          },
          {
            "name": "blk_write_time",
            "type": "float8",
            "line": 170
          },
          {
            "name": "wal_records",
            "type": "int8",
            "line": 171
          },
          {
            "name": "wal_bytes",
            "type": "numeric",
            "line": 172
          }
        ]
      },
      {
        "name": "pgfr.samples_ring",
        "line": 177,
        "columns": [
          {
            "name": "slot_id",
            "type": "int4",
            "line": 178
          },
          {
            "name": "captured_at",
            "type": "timestamptz",
            "line": 179
          },
          {
            "name": "epoch_seconds",
            "type": "int8",
            "line": 180
          }
        ]
      },
      {
        "name": "pgfr.wait_samples_ring",
        "line": 184,
        "columns": [
          {
            "name": "slot_id",
            "type": "int4",
            "line": 185
          },
          {
            "name": "row_num",
            "type": "int4",
            "line": 186
          },
          {
            "name": "backend_type",
            "type": "text",
            "line": 187
          },
          {
            "name": "wait_event_type",
            "type": "text",
            "line": 188
          },
          {
            "name": "wait_event",
            "type": "text",
            "line": 189
          },
          {
            "name": "state",
            "type": "text",
            "line": 190
          },
          {
            "name": "count",
            "type": "int4",
            "line": 191
          }
        ]
      },
      {
        "name": "pgfr.activity_samples_ring",
        "line": 196,
        "columns": [
          {
            "name": "slot_id",
            "type": "int4",
            "line": 197
          },
          {
            "name": "row_num",
            "type": "int4",
            "line": 198
          },
          {
            "name": "pid",
            "type": "int4",
            "line": 199
          },
          {
            "name": "usename",
            "type": "text",
            "line": 200
          },
          {
            "name": "application_name",
            "type": "text",
            "line": 201
          },
          {
            "name": "client_addr",
            "type": "inet",
            "line": 202
          },
          {
            "name": "backend_type",
            "type": "text",
            "line": 203
          },
          {
            "name": "state",
            "type": "text",
            "line": 204
          },
          {
            "name": "wait_event_type",
            "type": "text",
            "line": 205
          },
          {
            "name": "wait_event",
            "type": "text",
            "line": 206
          },
          {
            "name": "backend_start",
            "type": "timestamptz",
            "line": 207
          },
          {
            "name": "xact_start",
            "type": "timestamptz",
            "line": 208
          },
          {
            "name": "query_start",
            "type": "timestamptz",
            "line": 209
          },
          {
            "name": "state_change",
            "type": "timestamptz",
            "line": 210
          },
          {
            "name": "query_preview",
            "type": "text",
            "line": 211
          }
        ]
      },
      {
        "name": "pgfr.lock_samples_ring",
        "line": 216,
        "columns": [
          {
            "name": "slot_id",
            "type": "int4",
            "line": 217
          },
          {
            "name": "row_num",
            "type": "int4",
            "line": 218
          },
          {
            "name": "blocked_pid",
            "type": "int4",
            "line": 219
          },
          {
            "name": "blocked_user",
            "type": "text",
            "line": 220
          },
          {
            "name": "blocked_app",
            "type": "text",
            "line": 221
          },
          {
            "name": "blocked_query_preview",
            "type": "text",
            "line": 222
          },
          {
            "name": "blocked_duration",
            "type": "interval",
            "line": 223
          },
          {
            "name": "blocking_pid",
            "type": "int4",
            "line": 224
          },
          {
            "name": "blocking_user",
            "type": "text",
            "line": 225
          },
          {
            "name": "blocking_app",
            "type": "text",
            "line": 226
          },
          {
            "name": "blocking_query_preview",
            "type": "text",
            "line": 227
          },
          {
            "name": "lock_type",
            "type": "text",
            "line": 228
          },
          {
            "name": "locked_relation_oid",
            "type": "oid",
            "line": 229
          }
        ]
      },
      {
        "name": "pgfr.wait_event_aggregates",
        "line": 259,
        "columns": [
          {
            "name": "id",
            "type": "bigserial",
            "line": 260
          },
          {
            "name": "start_time",
            "type": "timestamptz",
            "line": 261
          },
          {
            "name": "end_time",
            "type": "timestamptz",
            "line": 262
          },
          {
            "name": "backend_type",
            "type": "text",
            "line": 263
          },
          {
            "name": "wait_event_type",
            "type": "text",
            "line": 264
          },
          {
            "name": "wait_event",
            "type": "text",
            "line": 265
          },
          {
            "name": "state",
            "type": "text",
            "line": 266
          },
          {
            "name": "sample_count",
            "type": "int4",
            "line": 267
          },
          {
            "name": "total_waiters",
            "type": "int8",
            "line": 268
          },
          {
            "name": "avg_waiters",
            "type": "numeric",
            "line": 269
          },
          {
            "name": "max_waiters",
            "type": "int4",
            "line": 270
          },
          {
            "name": "pct_of_samples",
            "type": "numeric",
            "line": 271
          }
        ]
      },
      {
        "name": "pgfr.lock_aggregates",
        "line": 283,
        "columns": [
          {
            "name": "id",
            "type": "bigserial",
            "line": 284
          },
          {
            "name": "start_time",
            "type": "timestamptz",
            "line": 285
          },
          {
            "name": "end_time",
            "type": "timestamptz",
            "line": 286
          },
          {
            "name": "blocked_user",
            "type": "text",
            "line": 287
          },
          {
            "name": "blocking_user",
            "type": "text",
            "line": 288
          },
          {
            "name": "lock_type",
            "type": "text",
            "line": 289
          },
          {
            "name": "locked_relation_oid",
            "type": "oid",
            "line": 290
          },
          {
            "name": "occurrence_count",
            "type": "int4",
            "line": 291
          },
          {
            "name": "max_duration",
            "type": "interval",
            "line": 292
          },
          {
            "name": "avg_duration",
            "type": "interval",
            "line": 293
          },
          {
            "name": "sample_query",
            "type": "text",
            "line": 294
          }
        ]
      },
      {
        "name": "pgfr.activity_aggregates",
        "line": 304,
        "columns": [
          {
            "name": "id",
            "type": "bigserial",
            "line": 305
          },
          {
            "name": "start_time",
            "type": "timestamptz",
            "line": 306
          },
          {
            "name": "end_time",
            "type": "timestamptz",
            "line": 307
          },
          {
            "name": "query_preview",
            "type": "text",
            "line": 308
          },
          {
            "name": "occurrence_count",
            "type": "int4",
            "line": 309
          },
          {
            "name": "max_duration",
            "type": "interval",
            "line": 310
          },
          {
            "name": "avg_duration",
            "type": "interval",
            "line": 311
          }
        ]
      },
      {
        "name": "pgfr.activity_samples_archive",
        "line": 321,
        "columns": [
          {
            "name": "id",
            "type": "bigserial",
            "line": 322
          },
          {
            "name": "sample_id",
            "type": "int8",
            "line": 323
          },
          {
            "name": "captured_at",
            "type": "timestamptz",
            "line": 324
          },
          {
            "name": "pid",
            "type": "int4",
            "line": 325
          },
          {
            "name": "usename",
            "type": "text",
            "line": 326
          },
          {
            "name": "application_name",
            "type": "text",
            "line": 327
          },
          {
            "name": "client_addr",
            "type": "inet",
            "line": 328
          },
          {
            "name": "backend_type",
            "type": "text",
            "line": 329
          },
          {
            "name": "state",
            "type": "text",
            "line": 330
          },
          {
            "name": "wait_event_type",
            "type": "text",
            "line": 331
          },
          {
            "name": "wait_event",
            "type": "text",
            "line": 332
          },
          {
            "name": "backend_start",
            "type": "timestamptz",
            "line": 333
          },
          {
            "name": "xact_start",
            "type": "timestamptz",
            "line": 334
          },
          {
            "name": "query_start",
            "type": "timestamptz",
            "line": 335
          },
          {
            "name": "state_change",
            "type": "timestamptz",
            "line": 336
          },
          {
            "name": "query_preview",
            "type": "text",
            "line": 337
          }
        ]
      },
      {
        "name": "pgfr.lock_samples_archive",
        "line": 351,
        "columns": [
          {
            "name": "id",
            "type": "bigserial",
            "line": 352
          },
          {
            "name": "sample_id",
            "type": "int8",
            "line": 353
          },
          {
            "name": "captured_at",
            "type": "timestamptz",
            "line": 354
          },
          {
            "name": "blocked_pid",
            "type": "int4",
            "line": 355
          },
          {
            "name": "blocked_user",
            "type": "text",
            "line": 356
          },
          {
            "name": "blocked_app",
            "type": "text",
            "line": 357
          },
          {
            "name": "blocked_query_preview",
            "type": "text",
            "line": 358
          },
          {
            "name": "blocked_duration",
            "type": "interval",
            "line": 359
          },
          {
            "name": "blocking_pid",
            "type": "int4",
            "line": 360
          },
          {
            "name": "blocking_user",
            "type": "text",
            "line": 361
          },
          {
            "name": "blocking_app",
            "type": "text",
            "line": 362
          },
          {
            "name": "blocking_query_preview",
            "type": "text",
            "line": 363
          },
          {
            "name": "lock_type",
            "type": "text",
            "line": 364
          },
          {
            "name": "locked_relation_oid",
            "type": "oid",
            "line": 365
          }
        ]
      },
      {
        "name": "pgfr.wait_samples_archive",
        "line": 381,
        "columns": [
          {
            "name": "id",
            "type": "bigserial",
            "line": 382
          },
          {
            "name": "sample_id",
            "type": "int8",
            "line": 383
          },
          {
            "name": "captured_at",
            "type": "timestamptz",
            "line": 384
          },
          {
            "name": "backend_type",
            "type": "text",
            "line": 385
          },
          {
            "name": "wait_event_type",
            "type": "text",
            "line": 386
          },
          {
            "name": "wait_event",
            "type": "text",
            "line": 387
          },
          {
            "name": "state",
            "type": "text",
            "line": 388
          },
          {
            "name": "count",
            "type": "int4",
            "line": 389
          }
        ]
      },
      {
        "name": "pgfr.table_snapshots",
        "line": 403,
        "columns": [
          {
            "name": "snapshot_id",
            "type": "int4",
            "line": 404
          },
          {
            "name": "schemaname",
            "type": "text",
            "line": 405
          },
          {
            "name": "relname",
            "type": "text",
            "line": 406
          },
          {
            "name": "relid",
            "type": "oid",
            "line": 407
          },
          {
            "name": "seq_scan",
            "type": "int8",
            "line": 408
          },
          {
            "name": "seq_tup_read",
            "type": "int8",
            "line": 409
          },
          {
            "name": "idx_scan",
            "type": "int8",
            "line": 410
          },
          {
            "name": "idx_tup_fetch",
            "type": "int8",
            "line": 411
          },
          {
            "name": "n_tup_ins",
            "type": "int8",
            "line": 412
          },
          {
            "name": "n_tup_upd",
            "type": "int8",
            "line": 413
          },
          {
            "name": "n_tup_del",
            "type": "int8",
            "line": 414
          },
          {
            "name": "n_tup_hot_upd",
            "type": "int8",
            "line": 415
          },
          {
            "name": "n_live_tup",
            "type": "int8",
            "line": 416
          },
          {
            "name": "n_dead_tup",
            "type": "int8",
            "line": 417
          },
          {
            "name": "n_mod_since_analyze",
            "type": "int8",
            "line": 418
          },
          {
            "name": "vacuum_count",
            "type": "int8",
            "line": 419
          },
          {
            "name": "autovacuum_count",
            "type": "int8",
            "line": 420
          },
          {
            "name": "analyze_count",
            "type": "int8",
            "line": 421
          },
          {
            "name": "autoanalyze_count",
            "type": "int8",
            "line": 422
          },
          {
            "name": "last_vacuum",
            "type": "timestamptz",
            "line": 423
          },
          {
            "name": "last_autovacuum",
            "type": "timestamptz",
            "line": 424
          },
          {
            "name": "last_analyze",
            "type": "timestamptz",
            "line": 425
          },
          {
            "name": "last_autoanalyze",
            "type": "timestamptz",
            "line": 426
          },
          {
            "name": "relfrozenxid_age",
            "type": "int4",
            "line": 427
          },
          {
            "name": "reltuples",
            "type": "int8",
            "line": 428
          },
          {
            "name": "vacuum_running",
            "type": "bool",
            "line": 429
          },
          {
            "name": "last_vacuum_duration_ms",
            "type": "int8",
            "line": 430
          },
          {
            "name": "table_size_bytes",
            "type": "int8",
            "line": 432
          },
          {
            "name": "total_size_bytes",
            "type": "int8",
            "line": 433
          },
          {
            "name": "indexes_size_bytes",
            "type": "int8",
            "line": 434
          }
        ]
      },
      {
        "name": "pgfr.index_snapshots",
        "line": 447,
        "columns": [
          {
            "name": "snapshot_id",
            "type": "int4",
            "line": 448
          },
          {
            "name": "schemaname",
            "type": "text",
            "line": 449
          },
          {
            "name": "relname",
            "type": "text",
            "line": 450
          },
          {
            "name": "indexrelname",
            "type": "text",
            "line": 451
          },
          {
            "name": "relid",
            "type": "oid",
            "line": 452
          },
          {
            "name": "indexrelid",
            "type": "oid",
            "line": 453
          },
          {
            "name": "idx_scan",
            "type": "int8",
            "line": 454
          },
          {
            "name": "idx_tup_read",
            "type": "int8",
            "line": 455
          },
          {
            "name": "idx_tup_fetch",
            "type": "int8",
            "line": 456
          },
          {
            "name": "index_size_bytes",
            "type": "int8",
            "line": 457
          }
        ]
      },
      {
        "name": "pgfr.config_snapshots",
        "line": 470,
        "columns": [
          {
            "name": "snapshot_id",
            "type": "int4",
            "line": 471
          },
          {
            "name": "name",
            "type": "text",
            "line": 472
          },
          {
            "name": "setting",
            "type": "text",
            "line": 473
          },
          {
            "name": "unit",
            "type": "text",
            "line": 474
          },
          {
            "name": "source",
            "type": "text",
            "line": 475
          },
          {
            "name": "sourcefile",
            "type": "text",
            "line": 476
          }
        ]
      },
      {
        "name": "pgfr.relation_names",
        "line": 487,
        "columns": [
          {
            "name": "oid",
            "type": "oid",
            "line": 488
          },
          {
            "name": "nspname",
            "type": "text",
            "line": 489
          },
          {
            "name": "relname",
            "type": "text",
            "line": 490
          }
        ]
      },
      {
        "name": "pgfr.db_role_config_snapshots",
        "line": 500,
        "columns": [
          {
            "name": "snapshot_id",
            "type": "int4",
            "line": 501
          },
          {
            "name": "database_name",
            "type": "text",
            "line": 502
          },
          {
            "name": "role_name",
            "type": "text",
            "line": 503
          },
          {
            "name": "parameter_name",
            "type": "text",
            "line": 504
          },
          {
            "name": "parameter_value",
            "type": "text",
            "line": 505
          }
        ]
      },
      {
        "name": "pgfr.config",
        "line": 659,
        "columns": [
          {
            "name": "key",
            "type": "text",
            "line": 660
          },
          {
            "name": "value",
            "type": "text",
            "line": 661
          },
          {
            "name": "updated_at",
            "type": "timestamptz",
            "line": 662
          }
        ]
      },
      {
        "name": "pgfr.collection_stats",
        "line": 878,
        "columns": [
          {
            "name": "id",
            "type": "serial",
            "line": 879
          },
          {
            "name": "collection_type",
            "type": "text",
            "line": 880
          },
          {
            "name": "started_at",
            "type": "timestamptz",
            "line": 881
          },
          {
            "name": "completed_at",
            "type": "timestamptz",
            "line": 882
          },
          {
            "name": "duration_ms",
            "type": "int4",
            "line": 883
          },
          {
            "name": "success",
            "type": "bool",
            "line": 884
          },
          {
            "name": "error_message",
            "type": "text",
            "line": 885
          },
          {
            "name": "skipped",
            "type": "bool",
            "line": 886
          },
          {
            "name": "skipped_reason",
            "type": "text",
            "line": 887
          },
          {
            "name": "sections_total",
            "type": "int4",
            "line": 888
          },
          {
            "name": "sections_succeeded",
            "type": "int4",
            "line": 889
          }
        ]
      }
    ],
    "functions": [
      {
        "name": "pgfr._pretty_bytes",
        "line": 514,
        "returns": "text"
      },
      {
        "name": "pgfr._interpolate_metric",
        "line": 531,
        "returns": "numeric"
      },
      {
        "name": "pgfr._populate_relation_names",
        "line": 585,
        "returns": "int4"
      },
      {
        "name": "pgfr._safe_relname",
        "line": 611,
        "returns": "text"
      },
      {
        "name": "pgfr._get_setting_from_snapshots",
        "line": 626,
        "returns": "text"
      },
      {
        "name": "pgfr._pg_version",
        "line": 650,
        "returns": "int4"
      },
      {
        "name": "pgfr._profile_settings",
        "line": 667,
        "returns": "record"
      },
      {
        "name": "pgfr._check_circuit_breaker",
        "line": 896,
        "returns": "bool"
      },
      {
        "name": "pgfr._record_collection_start",
        "line": 941,
        "returns": "int4"
      },
      {
        "name": "pgfr._record_collection_end",
        "line": 954,
        "returns": "void"
      },
      {
        "name": "pgfr._record_collection_skip",
        "line": 970,
        "returns": "void"
      },
      {
        "name": "pgfr._record_section_success",
        "line": 983,
        "returns": "void"
      },
      {
        "name": "pgfr._get_config",
        "line": 993,
        "returns": "text"
      },
      {
        "name": "pgfr._get_ring_buffer_slots",
        "line": 1004,
        "returns": "int4"
      },
      {
        "name": "pgfr._set_section_timeout",
        "line": 1014,
        "returns": "void"
      },
      {
        "name": "pgfr.validate_config",
        "line": 1030,
        "returns": "record"
      },
      {
        "name": "pgfr.validate_ring_configuration",
        "line": 1135,
        "returns": "record"
      },
      {
        "name": "pgfr._has_pg_stat_statements",
        "line": 1239,
        "returns": "bool"
      },
      {
        "name": "pgfr._check_statements_health",
        "line": 1249,
        "returns": "record"
      },
      {
        "name": "pgfr._check_schema_size",
        "line": 1301,
        "returns": "record"
      },
      {
        "name": "pgfr.sample",
        "line": 1485,
        "returns": "timestamptz"
      },
      {
        "name": "pgfr.flush_ring_to_aggregates",
        "line": 1864,
        "returns": "void"
      },
      {
        "name": "pgfr.archive_ring_samples",
        "line": 1949,
        "returns": "void"
      },
      {
        "name": "pgfr.cleanup_aggregates",
        "line": 2087,
        "returns": "void"
      },
      {
        "name": "pgfr._collect_table_stats",
        "line": 2138,
        "returns": "void"
      },
      {
        "name": "pgfr._collect_index_stats",
        "line": 2322,
        "returns": "void"
      },
      {
        "name": "pgfr._collect_config_snapshot",
        "line": 2360,
        "returns": "void"
      },
      {
        "name": "pgfr._collect_db_role_config_snapshot",
        "line": 2490,
        "returns": "void"
      },
      {
        "name": "pgfr.snapshot",
        "line": 2583,
        "returns": "timestamptz"
      },
      {
        "name": "pgfr.compare",
        "line": 3301,
        "returns": "record"
      },
      {
        "name": "pgfr._get_ring_retention_interval",
        "line": 3409,
        "returns": "interval"
      },
      {
        "name": "pgfr.recent_waits_current",
        "line": 3498,
        "returns": "record"
      },
      {
        "name": "pgfr.recent_activity_current",
        "line": 3523,
        "returns": "record"
      },
      {
        "name": "pgfr.recent_locks_current",
        "line": 3558,
        "returns": "record"
      },
      {
        "name": "pgfr.wait_summary",
        "line": 3668,
        "returns": "record"
      },
      {
        "name": "pgfr.statement_compare",
        "line": 3710,
        "returns": "record"
      },
      {
        "name": "pgfr.activity_at",
        "line": 3824,
        "returns": "record"
      },
      {
        "name": "pgfr.set_mode",
        "line": 3938,
        "returns": "text"
      },
      {
        "name": "pgfr.get_mode",
        "line": 4010,
        "returns": "record"
      },
      {
        "name": "pgfr.list_profiles",
        "line": 4033,
        "returns": "record"
      },
      {
        "name": "pgfr.get_optimization_profiles",
        "line": 4073,
        "returns": "record"
      },
      {
        "name": "pgfr.apply_optimization_profile",
        "line": 4114,
        "returns": "record"
      },
      {
        "name": "pgfr.explain_profile",
        "line": 4195,
        "returns": "record"
      },
      {
        "name": "pgfr.apply_profile",
        "line": 4223,
        "returns": "record"
      },
      {
        "name": "pgfr.get_current_profile",
        "line": 4277,
        "returns": "record"
      },
      {
        "name": "pgfr.cleanup",
        "line": 4330,
        "returns": "record"
      },
      {
        "name": "pgfr.ring_buffer_health",
        "line": 4402,
        "returns": "record"
      },
      {
        "name": "pgfr.disable",
        "line": 4457,
        "returns": "text"
      },
      {
        "name": "pgfr.configure_ring_autovacuum",
        "line": 4499,
        "returns": "text"
      },
      {
        "name": "pgfr.rebuild_ring_buffers",
        "line": 4525,
        "returns": "text"
      },
      {
        "name": "pgfr.enable",
        "line": 4612,
        "returns": "text"
      },
      {
        "name": "pgfr.health_check",
        "line": 4771,
        "returns": "record"
      },
      {
        "name": "pgfr.export_for_upgrade",
        "line": 4956,
        "returns": "record"
      },
      {
        "name": "pgfr.config_recommendations",
        "line": 5039,
        "returns": "record"
      }
    ],
    "views": [
      {
        "name": "pgfr.deltas",
        "line": 3250
      },
      {
        "name": "pgfr.recent_waits",
        "line": 3418
      },
      {
        "name": "pgfr.recent_activity",
        "line": 3431
      },
      {
        "name": "pgfr.recent_locks",
        "line": 3454
      },
      {
        "name": "pgfr.recent_idle_in_transaction",
        "line": 3476
      },
      {
        "name": "pgfr.recent_replication",
        "line": 3593
      },
      {
        "name": "pgfr.recent_vacuum_progress",
        "line": 3616
      },
      {
        "name": "pgfr.archiver_status",
        "line": 3644
      }
    ],
    "types": []
  },
  {
    "file": "_record/tests/07_pathology_generators.sql",
    "tables": [
      {
        "name": "test_lock_contention",
        "line": 25,
        "columns": [
          {
            "name": "id",
            "type": "int4",
            "line": 26
          },
          {
            "name": "value",
            "type": "int4",
            "line": 27
          }
        ]
      },
      {
        "name": "test_memory_pressure",
        "line": 106,
        "columns": [
          {
            "name": "id",
            "type": "int4",
            "line": 107
          },
          {
            "name": "data",
            "type": "text",
            "line": 108
          }
        ]
      },
      {
        "name": "test_cpu_intensive",
        "line": 231,
        "columns": [
          {
            "name": "id",
            "type": "int4",
            "line": 232
          },
          {
            "name": "value",
            "type": "numeric",
            "line": 233
          }
        ]
      },
      {
        "name": "test_slow_realtime",
        "line": 312,
        "columns": [
          {
            "name": "id",
            "type": "int4",
            "line": 313
          },
          {
            "name": "data",
            "type": "text",
            "line": 314
          }
        ]
      },
      {
        "name": "test_slow_queries",
        "line": 381,
        "columns": [
          {
            "name": "id",
            "type": "int4",
            "line": 382
          },
          {
            "name": "category",
            "type": "int4",
            "line": 383
          },
          {
            "name": "data",
            "type": "text",
            "line": 384
          },
          {
            "name": "created_at",
            "type": "timestamp",
            "line": 385
          }
        ]
      },
      {
        "name": "test_historical",
        "line": 619,
        "columns": [
          {
            "name": "id",
            "type": "int4",
            "line": 620
          },
          {
            "name": "data",
            "type": "text",
            "line": 621
          }
        ]
      },
      {
        "name": "test_disk_io",
        "line": 702,
        "columns": [
          {
            "name": "id",
            "type": "int4",
            "line": 703
          },
          {
            "name": "padding",
            "type": "text",
            "line": 704
          }
        ]
      }
    ],
    "functions": [],
    "views": [],
    "types": []
  },
  {
    "file": "_record/tests/08_pathology_value_checks.sql",
    "tables": [
      {
        "name": "vc_memory_test",
        "line": 18,
        "columns": [
          {
            "name": "id",
            "type": "int4",
            "line": 18
          },
          {
            "name": "data",
            "type": "text",
            "line": 18
          }
        ]
      },
      {
        "name": "vc_cpu_test",
        "line": 84,
        "columns": [
          {
            "name": "id",
            "type": "int4",
            "line": 84
          },
          {
            "name": "value",
            "type": "numeric",
            "line": 84
          }
        ]
      }
    ],
    "functions": [],
    "views": [],
    "types": []
  }
]
